acapy_controller/__init__.py
acapy_controller/controller.py
acapy_controller/events.py
acapy_controller/logging.py
acapy_controller/model_base.py
acapy_controller/models.py
acapy_controller/onboarding.py
acapy_controller/protocols.py
acapy_controller-0.3.0.dist-info/LICENSE
acapy_controller-0.3.0.dist-info/METADATA
acapy_controller-0.3.0.dist-info/WHEEL
acapy_controller-0.3.0.dist-info/RECORD
