Metadata-Version: 2.3
Name: acapy-controller
Version: 0.3.0
Summary: ACA-Py Controller
License: Apache-2.0
Author: Daniel Bluhm
Author-email: dbluhm@pm.me
Requires-Python: >=3.10,<4.0
Classifier: License :: OSI Approved :: Apache Software License
Classifier: Programming Language :: Python :: 3
Classifier: Programming Language :: Python :: 3.10
Classifier: Programming Language :: Python :: 3.11
Classifier: Programming Language :: Python :: 3.12
Classifier: Programming Language :: Python :: 3.13
Provides-Extra: models
Requires-Dist: aiohttp (>=3.9.5,<4.0.0)
Requires-Dist: async-selective-queue (>=0.1.1,<0.2.0)
Requires-Dist: blessings (>=1.7,<2.0)
Requires-Dist: pydantic (>=2.8.2,<3.0.0) ; extra == "models"
Project-URL: Homepage, https://github.com/indicio-tech/acapy-minimal-example
